tegracli/Makefile
tegracli/__init__.py
tegracli/dispatch.py
tegracli/group.py
tegracli/main.py
tegracli/make.bat
tegracli/types.py
tegracli/utilities.py
tegracli-0.2.7.dist-info/LICENSE
tegracli-0.2.7.dist-info/METADATA
tegracli-0.2.7.dist-info/WHEEL
tegracli-0.2.7.dist-info/entry_points.txt
tegracli-0.2.7.dist-info/RECORD
