Metadata-Version: 2.1
Name: tegracli
Version: 0.2.7
Summary: A research-focused Telegram CLI application
Home-page: https://pypi.org/project/tegracli/
License: MIT
Author: Philipp Kessling
Author-email: p.kessling@leibniz-hbi.de
Requires-Python: >=3.8,<4.0
Classifier: Development Status :: 3 - Alpha
Classifier: Environment :: Console
Classifier: Intended Audience :: Science/Research
Classifier: License :: OSI Approved :: MIT License
Classifier: Programming Language :: Python :: 3
Classifier: Programming Language :: Python :: 3.8
Classifier: Programming Language :: Python :: 3.9
Classifier: Programming Language :: Python :: 3.10
Classifier: Programming Language :: Python :: 3.11
Requires-Dist: PyYAML
Requires-Dist: Telethon
Requires-Dist: click
Requires-Dist: loguru
Requires-Dist: pandas
Requires-Dist: ujson
Project-URL: Repository, https://github.com/Leibniz-HBI/tegracli
